page_dewarp-0.2.7.dist-info/METADATA
page_dewarp-0.2.7.dist-info/WHEEL
page_dewarp-0.2.7.dist-info/entry_points.txt
page_dewarp-0.2.7.dist-info/licenses/LICENSE
page_dewarp/__init__.py
page_dewarp/__main__.py
page_dewarp/backends.py
page_dewarp/batch.py
page_dewarp/cli.py
page_dewarp/contours.py
page_dewarp/debug_utils/__init__.py
page_dewarp/debug_utils/colours.py
page_dewarp/debug_utils/viewer.py
page_dewarp/device.py
page_dewarp/dewarp.py
page_dewarp/image.py
page_dewarp/keypoints.py
page_dewarp/mask.py
page_dewarp/normalisation.py
page_dewarp/optimise/__init__.py
page_dewarp/optimise/_base.py
page_dewarp/optimise/_jax.py
page_dewarp/optimise/_jax_vmap.py
page_dewarp/optimise/_scipy.py
page_dewarp/options/__init__.py
page_dewarp/options/core.py
page_dewarp/options/k_opt.py
page_dewarp/projection.py
page_dewarp/simple_utils.py
page_dewarp/snoopy.py
page_dewarp/solve.py
page_dewarp/spans.py
page_dewarp-0.2.7.dist-info/RECORD
