Metadata-Version: 2.1
Name: page-dewarp
Version: 0.2.7
Summary: Page dewarping and thresholding using a cubic sheet model.
Keywords: computer vision,cubic spline,dewarping,document scanning,image correction,image processing
Author-Email: Louis Maddox <louismmx@gmail.com>
License: MIT
Classifier: Development Status :: 6 - Mature
Classifier: License :: OSI Approved :: MIT License
Classifier: Operating System :: OS Independent
Classifier: Programming Language :: Python :: 3.10
Classifier: Programming Language :: Python :: 3.11
Classifier: Programming Language :: Python :: 3.12
Classifier: Programming Language :: Python :: 3.13
Classifier: Programming Language :: Python :: 3.14
Classifier: Topic :: Multimedia :: Graphics :: Graphics Conversion
Classifier: Topic :: Scientific/Engineering :: Image Processing
Project-URL: Documentation, https://page-dewarp.vercel.app/
Project-URL: Homepage, https://github.com/lmmx/page-dewarp
Project-URL: Repository, https://github.com/lmmx/page-dewarp.git
Requires-Python: >=3.10
Requires-Dist: matplotlib
Requires-Dist: msgspec>=0.18.6
Requires-Dist: numpy>1.25
Requires-Dist: opencv-python
Requires-Dist: scipy
Requires-Dist: sympy
Provides-Extra: jax
Requires-Dist: jax>=0.6.2; extra == "jax"
